{
	"info": {
		"_postman_id": "5ee49b89-1030-4d8d-a24b-a85dc813b672",
		"name": "Project_2_Rest_booking",
		"schema": "https://schema.getpostman.com/json/collection/v2.1.0/collection.json",
		"_exporter_id": "44366601",
		"_collection_link": "https://api-testing-team-6691.postman.co/workspace/ATB_12X~707b2811-e945-41a4-8684-da1d8ffdb62b/collection/44366601-5ee49b89-1030-4d8d-a24b-a85dc813b672?action=share&source=collection_link&creator=44366601"
	},
	"item": [
		{
			"name": "Individual TC",
			"item": [
				{
					"name": "GET ALL THE BOOKING",
					"event": [
						{
							"listen": "test",
							"script": {
								"exec": [
									"pm.test(\"Status code is 200\", function () {\r",
									"    pm.response.to.have.status(200);\r",
									"});"
								],
								"type": "text/javascript",
								"packages": {}
							}
						}
					],
					"request": {
						"method": "GET",
						"header": [],
						"url": {
							"raw": "https://restful-booker.herokuapp.com/booking",
							"protocol": "https",
							"host": [
								"restful-booker",
								"herokuapp",
								"com"
							],
							"path": [
								"booking"
							]
						},
						"description": "Generated from cURL: curl -i https://restful-booker.herokuapp.com/booking\r\n"
					},
					"response": []
				},
				{
					"name": "GET SINGLE BOOKING",
					"event": [
						{
							"listen": "test",
							"script": {
								"exec": [
									"pm.test(\"Status code is 200\", function () {\r",
									"    pm.response.to.have.status(200);\r",
									"});"
								],
								"type": "text/javascript",
								"packages": {}
							}
						}
					],
					"request": {
						"method": "GET",
						"header": [],
						"url": {
							"raw": "https://restful-booker.herokuapp.com/booking/1",
							"protocol": "https",
							"host": [
								"restful-booker",
								"herokuapp",
								"com"
							],
							"path": [
								"booking",
								"1"
							]
						},
						"description": "Generated from cURL: curl -i https://restful-booker.herokuapp.com/booking/1\r\n"
					},
					"response": []
				},
				{
					"name": "CREATE BOOKING",
					"event": [
						{
							"listen": "test",
							"script": {
								"exec": [
									"pm.test(\"Status code is 200\", function () {\r",
									"    pm.response.to.have.status(200);\r",
									"});"
								],
								"type": "text/javascript",
								"packages": {}
							}
						}
					],
					"request": {
						"method": "POST",
						"header": [
							{
								"key": "Content-Type",
								"value": "application/json"
							}
						],
						"body": {
							"mode": "raw",
							"raw": "{\r\n    \"firstname\" : \"Jim\",\r\n    \"lastname\" : \"Brown\",\r\n    \"totalprice\" : 111,\r\n    \"depositpaid\" : true,\r\n    \"bookingdates\" : {\r\n        \"checkin\" : \"2018-01-01\",\r\n        \"checkout\" : \"2019-01-01\"\r\n    },\r\n    \"additionalneeds\" : \"Breakfast\"\r\n}",
							"options": {
								"raw": {
									"language": "json"
								}
							}
						},
						"url": {
							"raw": "https://restful-booker.herokuapp.com/booking",
							"protocol": "https",
							"host": [
								"restful-booker",
								"herokuapp",
								"com"
							],
							"path": [
								"booking"
							]
						},
						"description": "Generated from cURL: curl -X POST \\\r\n  https://restful-booker.herokuapp.com/booking \\\r\n  -H 'Content-Type: application/json' \\\r\n  -d '{\r\n    \"firstname\" : \"Jim\",\r\n    \"lastname\" : \"Brown\",\r\n    \"totalprice\" : 111,\r\n    \"depositpaid\" : true,\r\n    \"bookingdates\" : {\r\n        \"checkin\" : \"2018-01-01\",\r\n        \"checkout\" : \"2019-01-01\"\r\n    },\r\n    \"additionalneeds\" : \"Breakfast\"\r\n}'"
					},
					"response": []
				},
				{
					"name": "CREATE BOOKING TC AI",
					"event": [
						{
							"listen": "test",
							"script": {
								"exec": [
									"// Defined bookingid from response before usage\r",
									"const res = pm.response.json(); // Parse JSON once\r",
									"const bookingid = res.bookingid; // Capture bookingid\r",
									"\r",
									"// 1. Status code validation\r",
									"pm.test(\"Status code is 200\", function () {\r",
									"    pm.response.to.have.status(200);\r",
									"});\r",
									"\r",
									"// 2. Validate JSON response format\r",
									"pm.test(\"Response should be a valid JSON object\", function () {\r",
									"    pm.expect(res).to.be.an('object');\r",
									"});\r",
									"\r",
									"// 3. bookingid existence & type\r",
									"pm.test(\"bookingid exists and is a number\", function () {\r",
									"    pm.expect(res).to.have.property(\"bookingid\").that.is.a('number');\r",
									"});\r",
									"\r",
									"// 4. booking object existence\r",
									"pm.test(\"booking exists and is an object\", function () {\r",
									"    pm.expect(res).to.have.property(\"booking\").that.is.an('object');\r",
									"});\r",
									"\r",
									"// 5. firstname validation\r",
									"pm.test(\"firstname exists and is non-empty string\", function () {\r",
									"    pm.expect(res.booking.firstname).to.exist.and.to.be.a('string').and.to.have.lengthOf.at.least(1);\r",
									"});\r",
									"\r",
									"// 6. lastname validation\r",
									"pm.test(\"lastname exists and is non-empty string\", function () {\r",
									"    pm.expect(res.booking.lastname).to.exist.and.to.be.a('string').and.to.have.lengthOf.at.least(1);\r",
									"});\r",
									"\r",
									"// 7. totalprice validation\r",
									"pm.test(\"totalprice exists and is positive number\", function () {\r",
									"    pm.expect(res.booking.totalprice).to.be.a('number').and.to.be.above(0);\r",
									"});\r",
									"\r",
									"// 8. depositpaid validation\r",
									"pm.test(\"depositpaid exists and is boolean\", function () {\r",
									"    pm.expect(res.booking.depositpaid).to.be.a('boolean');\r",
									"});\r",
									"\r",
									"// 9. bookingdates existence\r",
									"pm.test(\"bookingdates exists and is an object\", function () {\r",
									"    pm.expect(res.booking.bookingdates).to.be.an('object');\r",
									"});\r",
									"\r",
									"// 10. checkin format validation\r",
									"pm.test(\"checkin is in YYYY-MM-DD format\", function () {\r",
									"    pm.expect(res.booking.bookingdates.checkin).to.match(/^\\d{4}-\\d{2}-\\d{2}$/);\r",
									"});\r",
									"\r",
									"// 11. checkout format validation\r",
									"pm.test(\"checkout is in YYYY-MM-DD format\", function () {\r",
									"    pm.expect(res.booking.bookingdates.checkout).to.match(/^\\d{4}-\\d{2}-\\d{2}$/);\r",
									"});\r",
									"\r",
									"// 12. checkin < checkout logic\r",
									"pm.test(\"checkin date is before checkout date\", function () {\r",
									"    let checkin = new Date(res.booking.bookingdates.checkin);\r",
									"    let checkout = new Date(res.booking.bookingdates.checkout);\r",
									"    pm.expect(checkin.getTime()).to.be.below(checkout.getTime());\r",
									"});\r",
									"\r",
									"// 13. additionalneeds validation\r",
									"pm.test(\"additionalneeds exists and is non-empty string\", function () {\r",
									"    pm.expect(res.booking.additionalneeds).to.be.a('string').and.to.have.lengthOf.at.least(1);\r",
									"});\r",
									"\r",
									"pm.environment.set(\"bookingid\", bookingid);\r",
									""
								],
								"type": "text/javascript",
								"packages": {}
							}
						}
					],
					"request": {
						"method": "POST",
						"header": [
							{
								"key": "Content-Type",
								"value": "application/json"
							}
						],
						"body": {
							"mode": "raw",
							"raw": "{\r\n    \"firstname\" : \"Jim\",\r\n    \"lastname\" : \"Brown\",\r\n    \"totalprice\" : 111,\r\n    \"depositpaid\" : true,\r\n    \"bookingdates\" : {\r\n        \"checkin\" : \"2018-01-01\",\r\n        \"checkout\" : \"2019-01-01\"\r\n    },\r\n    \"additionalneeds\" : \"Breakfast\"\r\n}",
							"options": {
								"raw": {
									"language": "json"
								}
							}
						},
						"url": {
							"raw": "https://restful-booker.herokuapp.com/booking",
							"protocol": "https",
							"host": [
								"restful-booker",
								"herokuapp",
								"com"
							],
							"path": [
								"booking"
							]
						},
						"description": "Generated from cURL: curl -X POST \\\r\n  https://restful-booker.herokuapp.com/booking \\\r\n  -H 'Content-Type: application/json' \\\r\n  -d '{\r\n    \"firstname\" : \"Jim\",\r\n    \"lastname\" : \"Brown\",\r\n    \"totalprice\" : 111,\r\n    \"depositpaid\" : true,\r\n    \"bookingdates\" : {\r\n        \"checkin\" : \"2018-01-01\",\r\n        \"checkout\" : \"2019-01-01\"\r\n    },\r\n    \"additionalneeds\" : \"Breakfast\"\r\n}'"
					},
					"response": []
				},
				{
					"name": "CREATE BOOKING ADV TC",
					"event": [
						{
							"listen": "test",
							"script": {
								"exec": [
									"console.log(\"After the request is sent\")\r",
									"\r",
									"pm.test(\"Status code is 200\",function(){\r",
									"    pm.expect(pm.response.code).to.equals(200);\r",
									"})\r",
									"\r",
									"\r",
									"pm.test(\"Verify that bookingid is not gretter than 0\", function(){\r",
									"    var responseJSON = pm.response.json();\r",
									"    var bookingid =responseJSON.bookingid;\r",
									"    console.log(bookingid)\r",
									"    var checkout = responseJSON[\"booking\"][\"bookingdates\"][\"checkout\"]\r",
									"    console.log(checkout)\r",
									"    pm.environment.set(\"bookingid\",bookingid)\r",
									"    console.log(bookingid)\r",
									"})"
								],
								"type": "text/javascript",
								"packages": {}
							}
						},
						{
							"listen": "prerequest",
							"script": {
								"exec": [
									"console.log(\"before the request is sent\");"
								],
								"type": "text/javascript",
								"packages": {}
							}
						}
					],
					"request": {
						"method": "POST",
						"header": [
							{
								"key": "Content-Type",
								"value": "application/json"
							}
						],
						"body": {
							"mode": "raw",
							"raw": "{\r\n    \"firstname\" : \"Jim\",\r\n    \"lastname\" : \"Brown\",\r\n    \"totalprice\" : 111,\r\n    \"depositpaid\" : true,\r\n    \"bookingdates\" : {\r\n        \"checkin\" : \"2018-01-01\",\r\n        \"checkout\" : \"2019-01-01\"\r\n    },\r\n    \"additionalneeds\" : \"Breakfast\"\r\n}",
							"options": {
								"raw": {
									"language": "json"
								}
							}
						},
						"url": {
							"raw": "https://restful-booker.herokuapp.com/booking",
							"protocol": "https",
							"host": [
								"restful-booker",
								"herokuapp",
								"com"
							],
							"path": [
								"booking"
							]
						},
						"description": "Generated from cURL: curl -X POST \\\r\n  https://restful-booker.herokuapp.com/booking \\\r\n  -H 'Content-Type: application/json' \\\r\n  -d '{\r\n    \"firstname\" : \"Jim\",\r\n    \"lastname\" : \"Brown\",\r\n    \"totalprice\" : 111,\r\n    \"depositpaid\" : true,\r\n    \"bookingdates\" : {\r\n        \"checkin\" : \"2018-01-01\",\r\n        \"checkout\" : \"2019-01-01\"\r\n    },\r\n    \"additionalneeds\" : \"Breakfast\"\r\n}'"
					},
					"response": []
				},
				{
					"name": "CREATE BOOKING large value",
					"event": [
						{
							"listen": "test",
							"script": {
								"exec": [
									"pm.test(\"API should return 400 Bad Request or 422 Unprocessable Entity\", function () {\r",
									"    pm.expect([400, 422]).to.include(pm.response.code);\r",
									"});"
								],
								"type": "text/javascript",
								"packages": {}
							}
						}
					],
					"request": {
						"method": "POST",
						"header": [
							{
								"key": "Content-Type",
								"value": "application/json"
							}
						],
						"body": {
							"mode": "raw",
							"raw": "{\r\n    \"firstname\" : \"Jim\",\r\n    \"lastname\" : \"Brown\",\r\n    \"totalprice\" : 11100000000000000000000000000000000000000000000000000000,\r\n    \"depositpaid\" : true,\r\n    \"bookingdates\" : {\r\n        \"checkin\" : \"2018-01-01\",\r\n        \"checkout\" : \"2019-01-01\"\r\n    },\r\n    \"additionalneeds\" : \"Breakfast\"\r\n}",
							"options": {
								"raw": {
									"language": "json"
								}
							}
						},
						"url": {
							"raw": "https://restful-booker.herokuapp.com/booking",
							"protocol": "https",
							"host": [
								"restful-booker",
								"herokuapp",
								"com"
							],
							"path": [
								"booking"
							]
						},
						"description": "Generated from cURL: curl -X POST \\\r\n  https://restful-booker.herokuapp.com/booking \\\r\n  -H 'Content-Type: application/json' \\\r\n  -d '{\r\n    \"firstname\" : \"Jim\",\r\n    \"lastname\" : \"Brown\",\r\n    \"totalprice\" : 111,\r\n    \"depositpaid\" : true,\r\n    \"bookingdates\" : {\r\n        \"checkin\" : \"2018-01-01\",\r\n        \"checkout\" : \"2019-01-01\"\r\n    },\r\n    \"additionalneeds\" : \"Breakfast\"\r\n}'"
					},
					"response": []
				},
				{
					"name": "CREATE BOOKING Negative-nobody",
					"event": [
						{
							"listen": "test",
							"script": {
								"exec": [
									"pm.test(\"for invoaid body Status code is 500\", function () {\r",
									"    pm.response.to.have.status(500);\r",
									"});"
								],
								"type": "text/javascript",
								"packages": {}
							}
						}
					],
					"request": {
						"method": "POST",
						"header": [
							{
								"key": "Content-Type",
								"value": "application/json"
							}
						],
						"body": {
							"mode": "raw",
							"raw": "",
							"options": {
								"raw": {
									"language": "json"
								}
							}
						},
						"url": {
							"raw": "https://restful-booker.herokuapp.com/booking",
							"protocol": "https",
							"host": [
								"restful-booker",
								"herokuapp",
								"com"
							],
							"path": [
								"booking"
							]
						},
						"description": "Generated from cURL: curl -X POST \\\r\n  https://restful-booker.herokuapp.com/booking \\\r\n  -H 'Content-Type: application/json' \\\r\n  -d '{\r\n    \"firstname\" : \"Jim\",\r\n    \"lastname\" : \"Brown\",\r\n    \"totalprice\" : 111,\r\n    \"depositpaid\" : true,\r\n    \"bookingdates\" : {\r\n        \"checkin\" : \"2018-01-01\",\r\n        \"checkout\" : \"2019-01-01\"\r\n    },\r\n    \"additionalneeds\" : \"Breakfast\"\r\n}'"
					},
					"response": []
				},
				{
					"name": "CREATE BOOKING TC_1 BY AI",
					"event": [
						{
							"listen": "test",
							"script": {
								"exec": [
									"pm.test(\"Response status code is 200\", function () {\r",
									"    pm.expect(pm.response.code).to.equal(200);\r",
									"});\r",
									"\r",
									"\r",
									"pm.test(\"Response time is less than 2000ms\", function () {\r",
									"    pm.expect(pm.response.responseTime).to.be.below(2000);\r",
									"});\r",
									"\r",
									"\r",
									"pm.test(\"Response matches the expected schema\", function () {\r",
									"    const responseData = pm.response.json();\r",
									"\r",
									"    pm.expect(responseData).to.be.an('object');\r",
									"    pm.expect(responseData).to.have.all.keys('bookingid', 'firstname', 'lastname', 'totalprice', 'depositpaid', 'bookingdates', 'additionalneeds');\r",
									"\r",
									"    pm.expect(responseData.firstname).to.be.a('string');\r",
									"    pm.expect(responseData.lastname).to.be.a('string');\r",
									"    pm.expect(responseData.totalprice).to.be.a('number');\r",
									"    pm.expect(responseData.depositpaid).to.be.a('boolean');\r",
									"\r",
									"    pm.expect(responseData.bookingdates).to.be.an('object');\r",
									"    pm.expect(responseData.bookingdates).to.have.all.keys('checkin', 'checkout');\r",
									"    pm.expect(responseData.bookingdates.checkin).to.be.a('string');\r",
									"    pm.expect(responseData.bookingdates.checkout).to.be.a('string');\r",
									"});\r",
									"\r",
									"\r",
									"pm.test(\"Firstname and lastname must be non-empty strings\", function () {\r",
									"    const responseData = pm.response.json();\r",
									"    \r",
									"    pm.expect(responseData).to.be.an('object');\r",
									"    pm.expect(responseData.firstname).to.exist.and.to.be.a('string').and.to.have.lengthOf.at.least(1, \"Firstname should not be empty\");\r",
									"    pm.expect(responseData.lastname).to.exist.and.to.be.a('string').and.to.have.lengthOf.at.least(1, \"Lastname should not be empty\");\r",
									"});\r",
									"\r",
									"\r",
									"pm.test(\"Totalprice must be a positive integer\", function () {\r",
									"    const responseData = pm.response.json();\r",
									"    \r",
									"    pm.expect(responseData).to.be.an('object');\r",
									"    pm.expect(responseData.totalprice).to.exist.and.to.be.a('number').and.to.be.above(0);\r",
									"});\r",
									""
								],
								"type": "text/javascript",
								"packages": {}
							}
						}
					],
					"request": {
						"method": "POST",
						"header": [
							{
								"key": "Content-Type",
								"value": "application/json"
							}
						],
						"body": {
							"mode": "raw",
							"raw": "{\r\n    \"firstname\" : \"Jim\",\r\n    \"lastname\" : \"Brown\",\r\n    \"totalprice\" : 111,\r\n    \"depositpaid\" : true,\r\n    \"bookingdates\" : {\r\n        \"checkin\" : \"2018-01-01\",\r\n        \"checkout\" : \"2019-01-01\"\r\n    },\r\n    \"additionalneeds\" : \"Breakfast\"\r\n}",
							"options": {
								"raw": {
									"language": "json"
								}
							}
						},
						"url": {
							"raw": "https://restful-booker.herokuapp.com/booking",
							"protocol": "https",
							"host": [
								"restful-booker",
								"herokuapp",
								"com"
							],
							"path": [
								"booking"
							]
						},
						"description": "Generated from cURL: curl -X POST \\\r\n  https://restful-booker.herokuapp.com/booking \\\r\n  -H 'Content-Type: application/json' \\\r\n  -d '{\r\n    \"firstname\" : \"Jim\",\r\n    \"lastname\" : \"Brown\",\r\n    \"totalprice\" : 111,\r\n    \"depositpaid\" : true,\r\n    \"bookingdates\" : {\r\n        \"checkin\" : \"2018-01-01\",\r\n        \"checkout\" : \"2019-01-01\"\r\n    },\r\n    \"additionalneeds\" : \"Breakfast\"\r\n}'"
					},
					"response": []
				},
				{
					"name": "CREATE BOOKING TC_1 BY SNIPPETS",
					"event": [
						{
							"listen": "test",
							"script": {
								"exec": [
									"pm.test(\"TC_1_Status code is 200\", function () {\r",
									"    pm.response.to.have.status(200);\r",
									"});\r",
									"pm.test(\"TC_2_Body matches string bookingid\", function () {\r",
									"    pm.expect(pm.response.text()).to.include(\"bookingid\");\r",
									"});\r",
									"pm.test(\"TC_3_Content-Type is present\", function () {\r",
									"    pm.response.to.have.header(\"Content-Type\");\r",
									"});\r",
									"pm.test(\"TC_4_Response time is less than 1500ms\", function () {\r",
									"    pm.expect(pm.response.responseTime).to.be.below(1500);\r",
									"});"
								],
								"type": "text/javascript",
								"packages": {}
							}
						}
					],
					"request": {
						"method": "POST",
						"header": [
							{
								"key": "Content-Type",
								"value": "application/json"
							}
						],
						"body": {
							"mode": "raw",
							"raw": "{\r\n    \"firstname\" : \"Jim\",\r\n    \"lastname\" : \"Brown\",\r\n    \"totalprice\" : 111,\r\n    \"depositpaid\" : true,\r\n    \"bookingdates\" : {\r\n        \"checkin\" : \"2018-01-01\",\r\n        \"checkout\" : \"2019-01-01\"\r\n    },\r\n    \"additionalneeds\" : \"Breakfast\"\r\n}",
							"options": {
								"raw": {
									"language": "json"
								}
							}
						},
						"url": {
							"raw": "https://restful-booker.herokuapp.com/booking",
							"protocol": "https",
							"host": [
								"restful-booker",
								"herokuapp",
								"com"
							],
							"path": [
								"booking"
							]
						},
						"description": "Generated from cURL: curl -X POST \\\r\n  https://restful-booker.herokuapp.com/booking \\\r\n  -H 'Content-Type: application/json' \\\r\n  -d '{\r\n    \"firstname\" : \"Jim\",\r\n    \"lastname\" : \"Brown\",\r\n    \"totalprice\" : 111,\r\n    \"depositpaid\" : true,\r\n    \"bookingdates\" : {\r\n        \"checkin\" : \"2018-01-01\",\r\n        \"checkout\" : \"2019-01-01\"\r\n    },\r\n    \"additionalneeds\" : \"Breakfast\"\r\n}'"
					},
					"response": []
				},
				{
					"name": "CREATE BOOKING TC_1 BY JS",
					"event": [
						{
							"listen": "test",
							"script": {
								"exec": [
									"pm.test(\"Status code is 200\", function () {\r",
									"    pm.response.to.have.status(200);\r",
									"});"
								],
								"type": "text/javascript",
								"packages": {}
							}
						}
					],
					"request": {
						"method": "POST",
						"header": [
							{
								"key": "Content-Type",
								"value": "application/json"
							}
						],
						"body": {
							"mode": "raw",
							"raw": "{\r\n    \"firstname\" : \"Jim\",\r\n    \"lastname\" : \"Brown\",\r\n    \"totalprice\" : 111,\r\n    \"depositpaid\" : true,\r\n    \"bookingdates\" : {\r\n        \"checkin\" : \"2018-01-01\",\r\n        \"checkout\" : \"2019-01-01\"\r\n    },\r\n    \"additionalneeds\" : \"Breakfast\"\r\n}",
							"options": {
								"raw": {
									"language": "json"
								}
							}
						},
						"url": {
							"raw": "https://restful-booker.herokuapp.com/booking",
							"protocol": "https",
							"host": [
								"restful-booker",
								"herokuapp",
								"com"
							],
							"path": [
								"booking"
							]
						},
						"description": "Generated from cURL: curl -X POST \\\r\n  https://restful-booker.herokuapp.com/booking \\\r\n  -H 'Content-Type: application/json' \\\r\n  -d '{\r\n    \"firstname\" : \"Jim\",\r\n    \"lastname\" : \"Brown\",\r\n    \"totalprice\" : 111,\r\n    \"depositpaid\" : true,\r\n    \"bookingdates\" : {\r\n        \"checkin\" : \"2018-01-01\",\r\n        \"checkout\" : \"2019-01-01\"\r\n    },\r\n    \"additionalneeds\" : \"Breakfast\"\r\n}'"
					},
					"response": []
				},
				{
					"name": "FULL UPDATE BOOKING",
					"event": [
						{
							"listen": "test",
							"script": {
								"exec": [
									"pm.test(\"Status code is 200\", function () {\r",
									"    pm.response.to.have.status(200);\r",
									"});"
								],
								"type": "text/javascript",
								"packages": {}
							}
						}
					],
					"request": {
						"auth": {
							"type": "noauth"
						},
						"method": "PUT",
						"header": [
							{
								"key": "Content-Type",
								"value": "application/json"
							},
							{
								"key": "Accept",
								"value": "application/json"
							},
							{
								"key": "Cookie",
								"value": "token=abc123"
							},
							{
								"key": "Authorization",
								"value": "Basic YWRtaW46cGFzc3dvcmQxMjM=",
								"type": "text"
							}
						],
						"body": {
							"mode": "raw",
							"raw": "{\r\n    \"firstname\" : \"James\",\r\n    \"lastname\" : \"Brown\",\r\n    \"totalprice\" : 111,\r\n    \"depositpaid\" : true,\r\n    \"bookingdates\" : {\r\n        \"checkin\" : \"2018-01-01\",\r\n        \"checkout\" : \"2019-01-01\"\r\n    },\r\n    \"additionalneeds\" : \"Breakfast\"\r\n}",
							"options": {
								"raw": {
									"language": "json"
								}
							}
						},
						"url": {
							"raw": "https://restful-booker.herokuapp.com/booking/3151",
							"protocol": "https",
							"host": [
								"restful-booker",
								"herokuapp",
								"com"
							],
							"path": [
								"booking",
								"3151"
							]
						},
						"description": "Generated from cURL: curl -X PUT \\\r\n  https://restful-booker.herokuapp.com/booking/1 \\\r\n  -H 'Content-Type: application/json' \\\r\n  -H 'Accept: application/json' \\\r\n  -H 'Cookie: token=abc123' \\\r\n  -d '{\r\n    \"firstname\" : \"James\",\r\n    \"lastname\" : \"Brown\",\r\n    \"totalprice\" : 111,\r\n    \"depositpaid\" : true,\r\n    \"bookingdates\" : {\r\n        \"checkin\" : \"2018-01-01\",\r\n        \"checkout\" : \"2019-01-01\"\r\n    },\r\n    \"additionalneeds\" : \"Breakfast\"\r\n}'"
					},
					"response": []
				},
				{
					"name": "PARTIAL UPDATE",
					"event": [
						{
							"listen": "test",
							"script": {
								"exec": [
									"pm.test(\"Status code is 200\", function () {\r",
									"    pm.response.to.have.status(200);\r",
									"});"
								],
								"type": "text/javascript",
								"packages": {}
							}
						}
					],
					"protocolProfileBehavior": {
						"disabledSystemHeaders": {}
					},
					"request": {
						"auth": {
							"type": "basic",
							"basic": [
								{
									"key": "password",
									"value": "password123",
									"type": "string"
								},
								{
									"key": "username",
									"value": "admin",
									"type": "string"
								}
							]
						},
						"method": "PATCH",
						"header": [
							{
								"key": "Content-Type",
								"value": "application/json"
							},
							{
								"key": "Accept",
								"value": "application/json"
							},
							{
								"key": "Cookie",
								"value": "token=abc123"
							}
						],
						"body": {
							"mode": "raw",
							"raw": "{\r\n    \"firstname\" : \"James\",\r\n    \"lastname\" : \"Brown\"\r\n}",
							"options": {
								"raw": {
									"language": "json"
								}
							}
						},
						"url": {
							"raw": "https://restful-booker.herokuapp.com/booking/2203",
							"protocol": "https",
							"host": [
								"restful-booker",
								"herokuapp",
								"com"
							],
							"path": [
								"booking",
								"2203"
							]
						},
						"description": "Generated from cURL: curl -X PUT \\\r\n  https://restful-booker.herokuapp.com/booking/1 \\\r\n  -H 'Content-Type: application/json' \\\r\n  -H 'Accept: application/json' \\\r\n  -H 'Cookie: token=abc123' \\\r\n  -d '{\r\n    \"firstname\" : \"James\",\r\n    \"lastname\" : \"Brown\"\r\n}'"
					},
					"response": []
				},
				{
					"name": "DELETE BOOKING BY ID",
					"event": [
						{
							"listen": "test",
							"script": {
								"exec": [
									"pm.test(\"Status code is 200\", function () {\r",
									"    pm.response.to.have.status(200);\r",
									"});"
								],
								"type": "text/javascript",
								"packages": {}
							}
						}
					],
					"request": {
						"method": "DELETE",
						"header": [
							{
								"key": "Content-Type",
								"value": "application/json"
							},
							{
								"key": "Cookie",
								"value": "token=abc123"
							}
						],
						"url": {
							"raw": "https://restful-booker.herokuapp.com/booking/1",
							"protocol": "https",
							"host": [
								"restful-booker",
								"herokuapp",
								"com"
							],
							"path": [
								"booking",
								"1"
							]
						},
						"description": "Generated from cURL: curl -X DELETE \\\r\n  https://restful-booker.herokuapp.com/booking/1 \\\r\n  -H 'Content-Type: application/json' \\\r\n  -H 'Cookie: token=abc123'"
					},
					"response": []
				},
				{
					"name": "PONG REQUEST",
					"event": [
						{
							"listen": "test",
							"script": {
								"exec": [
									"pm.test(\"Status code is 200\", function () {\r",
									"    pm.response.to.have.status(200);\r",
									"});"
								],
								"type": "text/javascript",
								"packages": {}
							}
						}
					],
					"request": {
						"method": "GET",
						"header": [],
						"url": {
							"raw": "https://restful-booker.herokuapp.com/ping",
							"protocol": "https",
							"host": [
								"restful-booker",
								"herokuapp",
								"com"
							],
							"path": [
								"ping"
							]
						},
						"description": "Generated from cURL: curl -i https://restful-booker.herokuapp.com/ping\r\n"
					},
					"response": []
				},
				{
					"name": "Auth - Create Token",
					"event": [
						{
							"listen": "test",
							"script": {
								"exec": [
									"pm.test(\"Status code is 200\", function () {\r",
									"    pm.response.to.have.status(200);\r",
									"});"
								],
								"type": "text/javascript",
								"packages": {}
							}
						}
					],
					"request": {
						"method": "POST",
						"header": [
							{
								"key": "Content-Type",
								"value": "application/json"
							}
						],
						"body": {
							"mode": "raw",
							"raw": "{\r\n    \"username\" : \"admin\",\r\n    \"password\" : \"password123\"\r\n}",
							"options": {
								"raw": {
									"language": "json"
								}
							}
						},
						"url": {
							"raw": "https://restful-booker.herokuapp.com/auth",
							"protocol": "https",
							"host": [
								"restful-booker",
								"herokuapp",
								"com"
							],
							"path": [
								"auth"
							]
						},
						"description": "Generated from cURL: curl -X POST \\\r\n  https://restful-booker.herokuapp.com/auth \\\r\n  -H 'Content-Type: application/json' \\\r\n  -d '{\r\n    \"username\" : \"admin\",\r\n    \"password\" : \"password123\"\r\n}'"
					},
					"response": []
				}
			]
		},
		{
			"name": "1.0. create  booking -> get the booking id",
			"item": [
				{
					"name": "CREATE BOOKING Copy",
					"event": [
						{
							"listen": "test",
							"script": {
								"exec": [
									"pm.test(\"Status code is 200\", function () {\r",
									"    pm.response.to.have.status(200);\r",
									"});\r",
									"\r",
									"pm.test(\"Verify that bookingid is not gretter than 0\", function () {\r",
									"    var bookingid = pm.response.json().bookingid;\r",
									"    pm.expect(bookingid).to.be.greaterThan(0)\r",
									"    pm.environment.set(\"bookingid\",bookingid)\r",
									"    console.log(bookingid)\r",
									"})\r",
									""
								],
								"type": "text/javascript",
								"packages": {}
							}
						}
					],
					"request": {
						"method": "POST",
						"header": [
							{
								"key": "Content-Type",
								"value": "application/json"
							}
						],
						"body": {
							"mode": "raw",
							"raw": "{\r\n    \"firstname\" : \"Jim\",\r\n    \"lastname\" : \"Brown\",\r\n    \"totalprice\" : 111,\r\n    \"depositpaid\" : true,\r\n    \"bookingdates\" : {\r\n        \"checkin\" : \"2018-01-01\",\r\n        \"checkout\" : \"2019-01-01\"\r\n    },\r\n    \"additionalneeds\" : \"Breakfast\"\r\n}",
							"options": {
								"raw": {
									"language": "json"
								}
							}
						},
						"url": {
							"raw": "https://restful-booker.herokuapp.com/booking",
							"protocol": "https",
							"host": [
								"restful-booker",
								"herokuapp",
								"com"
							],
							"path": [
								"booking"
							]
						},
						"description": "Generated from cURL: curl -X POST \\\r\n  https://restful-booker.herokuapp.com/booking \\\r\n  -H 'Content-Type: application/json' \\\r\n  -d '{\r\n    \"firstname\" : \"Jim\",\r\n    \"lastname\" : \"Brown\",\r\n    \"totalprice\" : 111,\r\n    \"depositpaid\" : true,\r\n    \"bookingdates\" : {\r\n        \"checkin\" : \"2018-01-01\",\r\n        \"checkout\" : \"2019-01-01\"\r\n    },\r\n    \"additionalneeds\" : \"Breakfast\"\r\n}'"
					},
					"response": []
				},
				{
					"name": "GET SINGLE BOOKING Copy",
					"event": [
						{
							"listen": "test",
							"script": {
								"exec": [
									"pm.test(\"Status code is 200\", function () {\r",
									"    pm.response.to.have.status(200);\r",
									"});"
								],
								"type": "text/javascript",
								"packages": {}
							}
						}
					],
					"request": {
						"method": "GET",
						"header": [],
						"url": {
							"raw": "https://restful-booker.herokuapp.com/booking/{{bookingid}}",
							"protocol": "https",
							"host": [
								"restful-booker",
								"herokuapp",
								"com"
							],
							"path": [
								"booking",
								"{{bookingid}}"
							]
						},
						"description": "Generated from cURL: curl -i https://restful-booker.herokuapp.com/booking/1\r\n"
					},
					"response": []
				},
				{
					"name": "DELETE BOOKING BY ID Copy",
					"event": [
						{
							"listen": "test",
							"script": {
								"exec": [
									"pm.test(\"Status code is 200\", function () {\r",
									"    pm.response.to.have.status(200);\r",
									"});"
								],
								"type": "text/javascript",
								"packages": {}
							}
						}
					],
					"request": {
						"auth": {
							"type": "basic",
							"basic": [
								{
									"key": "password",
									"value": "password123",
									"type": "string"
								},
								{
									"key": "username",
									"value": "admin",
									"type": "string"
								}
							]
						},
						"method": "DELETE",
						"header": [
							{
								"key": "Content-Type",
								"value": "application/json"
							},
							{
								"key": "Cookie",
								"value": "token=abc123"
							}
						],
						"url": {
							"raw": "https://restful-booker.herokuapp.com/booking/{{bookingid}}",
							"protocol": "https",
							"host": [
								"restful-booker",
								"herokuapp",
								"com"
							],
							"path": [
								"booking",
								"{{bookingid}}"
							]
						},
						"description": "Generated from cURL: curl -X DELETE \\\r\n  https://restful-booker.herokuapp.com/booking/1 \\\r\n  -H 'Content-Type: application/json' \\\r\n  -H 'Cookie: token=abc123'"
					},
					"response": []
				}
			]
		},
		{
			"name": "1.1. create  booking -> get the booking id, -> update it via the put request",
			"item": [
				{
					"name": "CREATE BOOKING Copy 2",
					"event": [
						{
							"listen": "test",
							"script": {
								"exec": [
									"pm.test(\"Status code is 200\", function () {\r",
									"    pm.response.to.have.status(200);\r",
									"});\r",
									"\r",
									"pm.test(\"Verify that bookingid is not gretter than 0\", function () {\r",
									"    var bookingid = pm.response.json().bookingid;\r",
									"    pm.expect(bookingid).to.be.greaterThan(0)\r",
									"    pm.environment.set(\"bookingid\",bookingid)\r",
									"    console.log(bookingid)\r",
									"})"
								],
								"type": "text/javascript",
								"packages": {}
							}
						}
					],
					"request": {
						"method": "POST",
						"header": [
							{
								"key": "Content-Type",
								"value": "application/json"
							}
						],
						"body": {
							"mode": "raw",
							"raw": "{\r\n    \"firstname\" : \"Jim\",\r\n    \"lastname\" : \"Brown\",\r\n    \"totalprice\" : 111,\r\n    \"depositpaid\" : true,\r\n    \"bookingdates\" : {\r\n        \"checkin\" : \"2018-01-01\",\r\n        \"checkout\" : \"2019-01-01\"\r\n    },\r\n    \"additionalneeds\" : \"Breakfast\"\r\n}",
							"options": {
								"raw": {
									"language": "json"
								}
							}
						},
						"url": {
							"raw": "https://restful-booker.herokuapp.com/booking",
							"protocol": "https",
							"host": [
								"restful-booker",
								"herokuapp",
								"com"
							],
							"path": [
								"booking"
							]
						},
						"description": "Generated from cURL: curl -X POST \\\r\n  https://restful-booker.herokuapp.com/booking \\\r\n  -H 'Content-Type: application/json' \\\r\n  -d '{\r\n    \"firstname\" : \"Jim\",\r\n    \"lastname\" : \"Brown\",\r\n    \"totalprice\" : 111,\r\n    \"depositpaid\" : true,\r\n    \"bookingdates\" : {\r\n        \"checkin\" : \"2018-01-01\",\r\n        \"checkout\" : \"2019-01-01\"\r\n    },\r\n    \"additionalneeds\" : \"Breakfast\"\r\n}'"
					},
					"response": []
				},
				{
					"name": "GET SINGLE BOOKING Copy 2",
					"event": [
						{
							"listen": "test",
							"script": {
								"exec": [
									"pm.test(\"Status code is 200\", function () {\r",
									"    pm.response.to.have.status(200);\r",
									"});"
								],
								"type": "text/javascript",
								"packages": {}
							}
						}
					],
					"request": {
						"method": "GET",
						"header": [],
						"url": {
							"raw": "https://restful-booker.herokuapp.com/booking/{{bookingid}}",
							"protocol": "https",
							"host": [
								"restful-booker",
								"herokuapp",
								"com"
							],
							"path": [
								"booking",
								"{{bookingid}}"
							]
						},
						"description": "Generated from cURL: curl -i https://restful-booker.herokuapp.com/booking/1\r\n"
					},
					"response": []
				},
				{
					"name": "FULL UPDATE BOOKING Copy",
					"event": [
						{
							"listen": "test",
							"script": {
								"exec": [
									"pm.test(\"Status code is 200\", function () {\r",
									"    pm.response.to.have.status(200);\r",
									"});"
								],
								"type": "text/javascript",
								"packages": {}
							}
						}
					],
					"request": {
						"auth": {
							"type": "noauth"
						},
						"method": "PUT",
						"header": [
							{
								"key": "Content-Type",
								"value": "application/json"
							},
							{
								"key": "Accept",
								"value": "application/json"
							},
							{
								"key": "Cookie",
								"value": "token=abc123"
							},
							{
								"key": "Authorization",
								"value": "Basic YWRtaW46cGFzc3dvcmQxMjM=",
								"type": "text"
							}
						],
						"body": {
							"mode": "raw",
							"raw": "{\r\n    \"firstname\" : \"James\",\r\n    \"lastname\" : \"Brown\",\r\n    \"totalprice\" : 111,\r\n    \"depositpaid\" : true,\r\n    \"bookingdates\" : {\r\n        \"checkin\" : \"2018-01-01\",\r\n        \"checkout\" : \"2019-01-01\"\r\n    },\r\n    \"additionalneeds\" : \"Breakfast\"\r\n}",
							"options": {
								"raw": {
									"language": "json"
								}
							}
						},
						"url": {
							"raw": "https://restful-booker.herokuapp.com/booking/{{bookingid}}",
							"protocol": "https",
							"host": [
								"restful-booker",
								"herokuapp",
								"com"
							],
							"path": [
								"booking",
								"{{bookingid}}"
							]
						},
						"description": "Generated from cURL: curl -X PUT \\\r\n  https://restful-booker.herokuapp.com/booking/1 \\\r\n  -H 'Content-Type: application/json' \\\r\n  -H 'Accept: application/json' \\\r\n  -H 'Cookie: token=abc123' \\\r\n  -d '{\r\n    \"firstname\" : \"James\",\r\n    \"lastname\" : \"Brown\",\r\n    \"totalprice\" : 111,\r\n    \"depositpaid\" : true,\r\n    \"bookingdates\" : {\r\n        \"checkin\" : \"2018-01-01\",\r\n        \"checkout\" : \"2019-01-01\"\r\n    },\r\n    \"additionalneeds\" : \"Breakfast\"\r\n}'"
					},
					"response": []
				}
			]
		},
		{
			"name": "1.2. create  booking -> get the booking id, -> update it via the patch request",
			"item": [
				{
					"name": "CREATE BOOKING Copy 3",
					"event": [
						{
							"listen": "test",
							"script": {
								"exec": [
									"pm.test(\"Status code is 200\", function () {\r",
									"    pm.response.to.have.status(200);\r",
									"});\r",
									"\r",
									"pm.test(\"Verify that bookingid is not gretter than 0\", function () {\r",
									"    var bookingid = pm.response.json().bookingid;\r",
									"    pm.expect(bookingid).to.be.greaterThan(0)\r",
									"    pm.environment.set(\"bookingid\",bookingid)\r",
									"    console.log(bookingid)\r",
									"})"
								],
								"type": "text/javascript",
								"packages": {}
							}
						}
					],
					"request": {
						"method": "POST",
						"header": [
							{
								"key": "Content-Type",
								"value": "application/json"
							}
						],
						"body": {
							"mode": "raw",
							"raw": "{\r\n    \"firstname\" : \"Jim\",\r\n    \"lastname\" : \"Brown\",\r\n    \"totalprice\" : 111,\r\n    \"depositpaid\" : true,\r\n    \"bookingdates\" : {\r\n        \"checkin\" : \"2018-01-01\",\r\n        \"checkout\" : \"2019-01-01\"\r\n    },\r\n    \"additionalneeds\" : \"Breakfast\"\r\n}",
							"options": {
								"raw": {
									"language": "json"
								}
							}
						},
						"url": {
							"raw": "https://restful-booker.herokuapp.com/booking",
							"protocol": "https",
							"host": [
								"restful-booker",
								"herokuapp",
								"com"
							],
							"path": [
								"booking"
							]
						},
						"description": "Generated from cURL: curl -X POST \\\r\n  https://restful-booker.herokuapp.com/booking \\\r\n  -H 'Content-Type: application/json' \\\r\n  -d '{\r\n    \"firstname\" : \"Jim\",\r\n    \"lastname\" : \"Brown\",\r\n    \"totalprice\" : 111,\r\n    \"depositpaid\" : true,\r\n    \"bookingdates\" : {\r\n        \"checkin\" : \"2018-01-01\",\r\n        \"checkout\" : \"2019-01-01\"\r\n    },\r\n    \"additionalneeds\" : \"Breakfast\"\r\n}'"
					},
					"response": []
				},
				{
					"name": "GET SINGLE BOOKING Copy 3",
					"event": [
						{
							"listen": "test",
							"script": {
								"exec": [
									"pm.test(\"Status code is 200\", function () {\r",
									"    pm.response.to.have.status(200);\r",
									"});"
								],
								"type": "text/javascript",
								"packages": {}
							}
						}
					],
					"request": {
						"method": "GET",
						"header": [],
						"url": {
							"raw": "https://restful-booker.herokuapp.com/booking/{{bookingid}}",
							"protocol": "https",
							"host": [
								"restful-booker",
								"herokuapp",
								"com"
							],
							"path": [
								"booking",
								"{{bookingid}}"
							]
						},
						"description": "Generated from cURL: curl -i https://restful-booker.herokuapp.com/booking/1\r\n"
					},
					"response": []
				},
				{
					"name": "PARTIAL UPDATE Copy",
					"event": [
						{
							"listen": "test",
							"script": {
								"exec": [
									"pm.test(\"Status code is 200\", function () {\r",
									"    pm.response.to.have.status(200);\r",
									"});"
								],
								"type": "text/javascript",
								"packages": {}
							}
						}
					],
					"request": {
						"auth": {
							"type": "basic",
							"basic": [
								{
									"key": "password",
									"value": "password123",
									"type": "string"
								},
								{
									"key": "username",
									"value": "admin",
									"type": "string"
								}
							]
						},
						"method": "PATCH",
						"header": [
							{
								"key": "Content-Type",
								"value": "application/json"
							},
							{
								"key": "Accept",
								"value": "application/json"
							},
							{
								"key": "Cookie",
								"value": "token=abc123"
							}
						],
						"body": {
							"mode": "raw",
							"raw": "{\r\n    \"firstname\" : \"James\",\r\n    \"lastname\" : \"White\"\r\n}",
							"options": {
								"raw": {
									"language": "json"
								}
							}
						},
						"url": {
							"raw": "https://restful-booker.herokuapp.com/booking/{{bookingid}}",
							"protocol": "https",
							"host": [
								"restful-booker",
								"herokuapp",
								"com"
							],
							"path": [
								"booking",
								"{{bookingid}}"
							]
						},
						"description": "Generated from cURL: curl -X PUT \\\r\n  https://restful-booker.herokuapp.com/booking/1 \\\r\n  -H 'Content-Type: application/json' \\\r\n  -H 'Accept: application/json' \\\r\n  -H 'Cookie: token=abc123' \\\r\n  -d '{\r\n    \"firstname\" : \"James\",\r\n    \"lastname\" : \"Brown\"\r\n}'"
					},
					"response": []
				}
			]
		},
		{
			"name": "1.3. create  booking -> get the booking id, -> update it via the put request -> verify id -> delete it",
			"item": [
				{
					"name": "CREATE BOOKING Copy 2",
					"event": [
						{
							"listen": "test",
							"script": {
								"exec": [
									"pm.test(\"Status code is 200\", function () {\r",
									"    pm.response.to.have.status(200);\r",
									"});\r",
									"pm.test(\"Verify that bookingid is not gretter than 0\", function () {\r",
									"    var bookingid = pm.response.json().bookingid;\r",
									"    pm.expect(bookingid).to.be.greaterThan(0)\r",
									"    pm.environment.set(\"bookingid\",bookingid)\r",
									"    console.log(bookingid)\r",
									"})"
								],
								"type": "text/javascript",
								"packages": {}
							}
						}
					],
					"request": {
						"method": "POST",
						"header": [
							{
								"key": "Content-Type",
								"value": "application/json"
							}
						],
						"body": {
							"mode": "raw",
							"raw": "{\r\n    \"firstname\" : \"Jim\",\r\n    \"lastname\" : \"Brown\",\r\n    \"totalprice\" : 111,\r\n    \"depositpaid\" : true,\r\n    \"bookingdates\" : {\r\n        \"checkin\" : \"2018-01-01\",\r\n        \"checkout\" : \"2019-01-01\"\r\n    },\r\n    \"additionalneeds\" : \"Breakfast\"\r\n}",
							"options": {
								"raw": {
									"language": "json"
								}
							}
						},
						"url": {
							"raw": "https://restful-booker.herokuapp.com/booking",
							"protocol": "https",
							"host": [
								"restful-booker",
								"herokuapp",
								"com"
							],
							"path": [
								"booking"
							]
						},
						"description": "Generated from cURL: curl -X POST \\\r\n  https://restful-booker.herokuapp.com/booking \\\r\n  -H 'Content-Type: application/json' \\\r\n  -d '{\r\n    \"firstname\" : \"Jim\",\r\n    \"lastname\" : \"Brown\",\r\n    \"totalprice\" : 111,\r\n    \"depositpaid\" : true,\r\n    \"bookingdates\" : {\r\n        \"checkin\" : \"2018-01-01\",\r\n        \"checkout\" : \"2019-01-01\"\r\n    },\r\n    \"additionalneeds\" : \"Breakfast\"\r\n}'"
					},
					"response": []
				},
				{
					"name": "GET SINGLE BOOKING Copy 3",
					"event": [
						{
							"listen": "test",
							"script": {
								"exec": [
									"pm.test(\"Status code is 200\", function () {\r",
									"    pm.response.to.have.status(200);\r",
									"});"
								],
								"type": "text/javascript",
								"packages": {}
							}
						}
					],
					"request": {
						"method": "GET",
						"header": [],
						"url": {
							"raw": "https://restful-booker.herokuapp.com/booking/{{bookingid}}",
							"protocol": "https",
							"host": [
								"restful-booker",
								"herokuapp",
								"com"
							],
							"path": [
								"booking",
								"{{bookingid}}"
							]
						},
						"description": "Generated from cURL: curl -i https://restful-booker.herokuapp.com/booking/1\r\n"
					},
					"response": []
				},
				{
					"name": "FULL UPDATE BOOKING Copy 2",
					"event": [
						{
							"listen": "test",
							"script": {
								"exec": [
									"pm.test(\"Status code is 200\", function () {\r",
									"    pm.response.to.have.status(200);\r",
									"});"
								],
								"type": "text/javascript",
								"packages": {}
							}
						}
					],
					"request": {
						"auth": {
							"type": "noauth"
						},
						"method": "PUT",
						"header": [
							{
								"key": "Content-Type",
								"value": "application/json"
							},
							{
								"key": "Accept",
								"value": "application/json"
							},
							{
								"key": "Cookie",
								"value": "token=abc123"
							},
							{
								"key": "Authorization",
								"value": "Basic YWRtaW46cGFzc3dvcmQxMjM=",
								"type": "text"
							}
						],
						"body": {
							"mode": "raw",
							"raw": "{\r\n    \"firstname\" : \"James\",\r\n    \"lastname\" : \"Brown\",\r\n    \"totalprice\" : 111,\r\n    \"depositpaid\" : true,\r\n    \"bookingdates\" : {\r\n        \"checkin\" : \"2018-01-01\",\r\n        \"checkout\" : \"2019-01-01\"\r\n    },\r\n    \"additionalneeds\" : \"Breakfast\"\r\n}",
							"options": {
								"raw": {
									"language": "json"
								}
							}
						},
						"url": {
							"raw": "https://restful-booker.herokuapp.com/booking/{{bookingid}}",
							"protocol": "https",
							"host": [
								"restful-booker",
								"herokuapp",
								"com"
							],
							"path": [
								"booking",
								"{{bookingid}}"
							]
						},
						"description": "Generated from cURL: curl -X PUT \\\r\n  https://restful-booker.herokuapp.com/booking/1 \\\r\n  -H 'Content-Type: application/json' \\\r\n  -H 'Accept: application/json' \\\r\n  -H 'Cookie: token=abc123' \\\r\n  -d '{\r\n    \"firstname\" : \"James\",\r\n    \"lastname\" : \"Brown\",\r\n    \"totalprice\" : 111,\r\n    \"depositpaid\" : true,\r\n    \"bookingdates\" : {\r\n        \"checkin\" : \"2018-01-01\",\r\n        \"checkout\" : \"2019-01-01\"\r\n    },\r\n    \"additionalneeds\" : \"Breakfast\"\r\n}'"
					},
					"response": []
				},
				{
					"name": "DELETE BOOKING BY ID Copy 2",
					"event": [
						{
							"listen": "test",
							"script": {
								"exec": [
									"pm.test(\"Status code is 200\", function () {\r",
									"    pm.response.to.have.status(200);\r",
									"});"
								],
								"type": "text/javascript",
								"packages": {}
							}
						}
					],
					"request": {
						"auth": {
							"type": "basic",
							"basic": [
								{
									"key": "password",
									"value": "password123",
									"type": "string"
								},
								{
									"key": "username",
									"value": "admin",
									"type": "string"
								}
							]
						},
						"method": "DELETE",
						"header": [
							{
								"key": "Content-Type",
								"value": "application/json"
							},
							{
								"key": "Cookie",
								"value": "token=abc123"
							}
						],
						"url": {
							"raw": "https://restful-booker.herokuapp.com/booking/{{bookingid}}",
							"protocol": "https",
							"host": [
								"restful-booker",
								"herokuapp",
								"com"
							],
							"path": [
								"booking",
								"{{bookingid}}"
							]
						},
						"description": "Generated from cURL: curl -X DELETE \\\r\n  https://restful-booker.herokuapp.com/booking/1 \\\r\n  -H 'Content-Type: application/json' \\\r\n  -H 'Cookie: token=abc123'"
					},
					"response": []
				}
			]
		}
	],
	"event": [
		{
			"listen": "prerequest",
			"script": {
				"type": "text/javascript",
				"packages": {},
				"exec": [
					""
				]
			}
		},
		{
			"listen": "test",
			"script": {
				"type": "text/javascript",
				"packages": {},
				"exec": [
					""
				]
			}
		}
	],
	"variable": [
		{
			"key": "c_variable",
			"value": "99",
			"type": "string"
		},
		{
			"key": "88",
			"value": ""
		},
		{
			"key": "bookingid",
			"value": ""
		}
	]
}